flamel/__init__.py
flamel/_version.py
flamel/flamel.py
flamel/py.typed
flamel/tests/__init__.py
flamel/tests/test_flamel.py
alchemistry_flamel-0.3.1.dist-info/AUTHORS
alchemistry_flamel-0.3.1.dist-info/LICENSE
alchemistry_flamel-0.3.1.dist-info/METADATA
alchemistry_flamel-0.3.1.dist-info/WHEEL
alchemistry_flamel-0.3.1.dist-info/entry_points.txt
alchemistry_flamel-0.3.1.dist-info/top_level.txt
alchemistry_flamel-0.3.1.dist-info/RECORD
