Metadata-Version: 2.1
Name: alchemistry-flamel
Version: 0.3.1
Summary: A command line interface (CLI) to alchemlyb.
Author-email: alchemistry <william@zhiyiwu.me>
License: BSD-3-Clause
Project-URL: Source, https://github.com/alchemistry/flamel/
Project-URL: Documentation, https://github.com/alchemistry/flamel/blob/master/README.md
Project-URL: Issue Tracker, https://github.com/alchemistry/flamel/issues
Project-URL: Discussions, https://github.com/alchemistry/flamel/discussions
Classifier: Development Status :: 3 - Alpha
Classifier: Environment :: Console
Classifier: Intended Audience :: Science/Research
Classifier: License :: OSI Approved :: BSD License
Classifier: Operating System :: POSIX
Classifier: Operating System :: MacOS :: MacOS X
Classifier: Operating System :: Microsoft :: Windows 
Classifier: Programming Language :: Python
Classifier: Programming Language :: Python :: 3
Classifier: Programming Language :: Python :: 3.8
Classifier: Programming Language :: Python :: 3.9
Classifier: Programming Language :: Python :: 3.10
Classifier: Programming Language :: Python :: 3.11
Classifier: Topic :: Scientific/Engineering
Classifier: Topic :: Scientific/Engineering :: Chemistry
Requires-Python: >=3.8
License-File: LICENSE
License-File: AUTHORS
Requires-Dist: alchemlyb (>=1.0)
Requires-Dist: importlib-resources ; python_version < "3.12"
Provides-Extra: test
Requires-Dist: pytest (>=6.1.2) ; extra == 'test'
Requires-Dist: pytest-runner ; extra == 'test'
Requires-Dist: pytest-mock ; extra == 'test'
